on_this_day/__init__.py
on_this_day/__main__.py
on_this_day-1.0.1.dist-info/METADATA
on_this_day-1.0.1.dist-info/WHEEL
on_this_day-1.0.1.dist-info/entry_points.txt
on_this_day-1.0.1.dist-info/top_level.txt
on_this_day-1.0.1.dist-info/RECORD
