Metadata-Version: 2.1
Name: on-this-day
Version: 1.0.1
Summary: What happened on this day on the past
Home-page: https://github.com/thevirusx3/on-this-day
Author: Saroj Bhattarai
Author-email: sarojbhattarai2053@gmail.com
License: MIT
Platform: UNKNOWN
Classifier: License :: OSI Approved :: MIT License
Classifier: Programming Language :: Python
Classifier: Programming Language :: Python :: 2
Classifier: Programming Language :: Python :: 3
Requires-Dist: beautifulsoup4
Requires-Dist: requests
